SwiftLibrary/GetAdress.py
SwiftLibrary/Method.py
SwiftLibrary/SendData.py
SwiftLibrary/__init__.py
SwiftLibrary-1.0.0.dist-info/LICENCE
SwiftLibrary-1.0.0.dist-info/METADATA
SwiftLibrary-1.0.0.dist-info/WHEEL
SwiftLibrary-1.0.0.dist-info/top_level.txt
SwiftLibrary-1.0.0.dist-info/RECORD
