Metadata-Version: 2.1
Name: SwiftLibrary
Version: 1.0.0
Summary: Swift Rubika is a simple and fast Rubika Messenger library built for you
Home-page: https://github.com/mester-root/rubx
Author: Mohamad Dark
Author-email: mr.mohamad.dark@gmail.com
License: MIT
Keywords: Swiftlibrary,messenger,python2,python,python3,api,self,Rubx,Rubika,SwiftRubika,rubix,rubikax,rubika,bot,robot,library,rubikalib,rubikalibrary,rubika.ir,librarySwiftRubika,m.rubika.ir
Classifier: Programming Language :: Python :: 3.6
Classifier: Programming Language :: Python :: 3.7
Classifier: Programming Language :: Python :: 3.8
Classifier: Programming Language :: Python :: 3.9
Classifier: Programming Language :: Python :: 3.10
Classifier: Programming Language :: Python :: 3.11
Classifier: License :: OSI Approved :: MIT License
Requires-Python: ~=3.7
License-File: LICENCE
Requires-Dist: requests
Requires-Dist: urllib3
Requires-Dist: pycryptodome
Requires-Dist: colorama
Requires-Dist: tinytag
